Workbook

Sheet README & Conventions
A1: Freyja — Anthropometric Reference: Body Segment Inertial Parameters
A3: Purpose | B3: Single source of truth for segment mass, centre-of-mass, and full inertia tensor. Every CAD/control decision references these values. Normalized parameters live here once; the 170 cm / 65 kg instantiation is computed by formula so a stature or mass change propagates from one cell.
A5: INSTANTIATION
A6: Total body mass | B6: 65 kg (set on 'BSIP Reference' B1 — blue input)
A7: Stature | B7: 1700 mm (set on 'BSIP Reference' B2 — blue input)
A8: Population provenance | B8: Dumas (2007) female = adjusted from Young et al. (1983), USAF women. Young, fit cohort — NOT a population-median female. Document deviations against this, do not assume it is a median.
A10: COORDINATE SYSTEM (ISB / Dumas segment frames)
A11: Axes (right-handed) | B11: +x anterior, +y cranial (up), +z to the subject's right.
A12: Pelvis frame | B12: Origin = right hip joint centre. x = anterior, normal to the plane of the two ASIS and the PSIS midpoint. z = parallel to the inter-ASIS line, pointing right. y = up, completing the triad. Build the Fusion pelvis CSYS to match this so the CoM vector and tensor drop in with no re-rotation.
A13: Each segment | B13: has its own SCS per Dumas/ISB. CoM vectors and tensors are expressed in that segment's frame — match each Fusion segment CSYS to its Dumas frame.
A14: Reference pose | B14: Anatomical neutral standing. Joint angle sign conventions per ISB JCS (adopt Grood-Suntay for the knee when that row is added).
A16: UNITS POLICY
A17: Mass | B17: kg
A18: Length / CoM offsets | B18: mm (CAD-native)
A19: Inertia | B19: kg·m² (biomech/sim standard; ×1e6 → kg·mm² for Fusion if needed)
A20: Dumas normalized inputs | B20: Enter EXACTLY as published: mass as fraction of body mass; CoM and radii of gyration as PERCENT of segment length (the sheet divides by 100). Entering them as published = fewest transcription transforms = fewest errors.
A22: SOURCE COMMITMENT (locked)
A23: Mass / CoM / inertia tensor | B23: Dumas (2007) female — PRIMARY. + Corrigendum 2007b for Head & Neck. + Dumas (2015) for Thorax & Abdomen. de Leva female = cross-check (limbs only — see below).
A24: Hip joint centre | B24: Harrington (2007), pelvic-dimension regression — PRIMARY. Bell (1990) = secondary cross-check.
A25: Knee / ankle JC | B25: Landmark midpoints (femoral epicondyles / malleoli), not a regression.
A26: Range of motion | B26: Anatomical ceiling: Boone & Azen / AAOS. Functional target: gait/stair/sit-to-stand kinematics. Keep as two columns.
A27: External body dimensions | B27: MakeHuman mesh = authoritative (envelope-first). ANSUR II female = reality-check on the mesh's driving girths/breadths.
A28: Segment density | B28: Derived sanity read-out from Fusion mass properties, not an independent target. Dempster/Winter values for eyeballing only.
A30: KEY CAVEATS
A31: Product-of-inertia sign | B31: Sheet uses I_ij = SIGN(r_ij)·m·(r_ij·L)² with r_ij the signed off-diagonal radius of gyration (% of L). CONFIRM this against Dumas (2007) inertia-matrix equation before trusting the products — the sign is the single easiest term to get wrong.
A32: de Leva cross-check | B32: Clean only for limb segments. de Leva carries one trunk segment; Dumas splits Thorax/Abdomen/Pelvis. For the trunk, compare LUMPED (sum Dumas's three) — not row-by-row.
A33: Pelvis SEGMENT mass ≠ structural mass | B33: Dumas 'pelvis' is the whole biomechanical segment: bone + gluteal/pelvic soft tissue + lower viscera. The target is Freyja's ENTIRE pelvis segment (structure + battery + flesh + skin), NOT the ~8 kg structural assembly alone. Do not compare 8 kg of hardware to the Dumas segment mass directly.
A34: Pelvis length definition | B34: Dumas normalizes the pelvis by its segment length = hip-JC midpoint to the lumbosacral (L5/S1) joint centre. Pin this exact endpoint from the paper before instantiating — pelvis length varies most by definition between sources.
A36: HOW TO USE
A37: 1 | B37: Fill the YELLOW cells on 'BSIP Reference': segment length L (from MakeHuman/your geometry) and the Dumas normalized values (transcribe from your copy of the paper).
A38: 2 | B38: Targets (mass kg, CoM mm, inertia kg·m²) compute automatically.
A39: 3 | B39: On 'Validation', paste Fusion mass-properties into the YELLOW achieved cells; deviations compute. Log any deliberate departure from biology with magnitude + expected control cost.
A40: 4 | B40: Check the count-weighted mass-fraction sum (≈1.000) reconstructs body mass — your transcription tripwire.
A42: Colour key | B42: Blue = hardcoded input • Black = formula • Green = link to another sheet • Yellow fill = needs your entry

Sheet BSIP Reference
A1: Total body mass (kg) | B1: 65
A2: Stature (mm) | B2: 1700
A4: PER-SEGMENT BSIP — Dumas (2007/2015) female, instantiated for the values above
A5: Segment | B5: Count | C5: Source / version | D5: L (mm) | E5: Mass frac | F5: Mass target (kg) | G5: CoM x (%L,+ant) | H5: CoM y (%L,+up) | I5: CoM z (%L,+R) | J5: CoM x (mm) | K5: CoM y (mm) | L5: CoM z (mm) | M5: rg x (%L) | N5: rg y (%L) | O5: rg z (%L) | P5: rg xy (%L,±) | Q5: rg yz (%L,±) | R5: rg xz (%L,±) | S5: Ixx (kg·m²) | T5: Iyy (kg·m²) | U5: Izz (kg·m²) | V5: Ixy (kg·m²,±) | W5: Iyz (kg·m²,±) | X5: Ixz (kg·m²,±) | Y5: Notes
A6: Head & Neck | B6: 1 | C6: Dumas 2007 + corrig. 2007b ✓ | D6: 253 | E6: 6.7 | F6: =E6/100*$B$1 -> 4.355 | G6: 1.6 | H6: 57.5 | I6: 0.1 | J6: =D6*G6/100 -> 4.048 | K6: =D6*H6/100 -> 145.475 | L6: =D6*I6/100 -> 0.253 | M6: 29 | N6: 23 | O6: 30 | P6: -4 | Q6: 0 | R6: 1 | S6: =F6*(M6/100*D6/1000)^2 -> 0.023443648 | T6: =F6*(N6/100*D6/1000)^2 -> 0.014746361 | U6: =F6*(O6/100*D6/1000)^2 -> 0.025088328 | V6: =SIGN(P6)*F6*(ABS(P6)/100*D6/1000)^2 -> -0.00044601471 | W6: =SIGN(Q6)*F6*(ABS(Q6)/100*D6/1000)^2 -> 0 | X6: =SIGN(R6)*F6*(ABS(R6)/100*D6/1000)^2 -> 2.7875919e-05 | Y6: CORRIGENDUM (2007b) values — NOT original 2007 Table 2. L=253 F. Origin=CJC. rxy=4(i)=negative.
A7: Thorax | B7: 1 | C7: Dumas 2015 ✓ | D7: 313 | E7: 26.3 | F7: =E7/100*$B$1 -> 17.095 | G7: 2.1 | H7: -52.8 | I7: 0.1 | J7: =D7*G7/100 -> 6.573 | K7: =D7*H7/100 -> -165.264 | L7: =D7*I7/100 -> 0.313 | M7: 39 | N7: 33 | O7: 35 | P7: -12 | Q7: 1 | R7: -3 | S7: =F7*(M7/100*D7/1000)^2 -> 0.25473405 | T7: =F7*(N7/100*D7/1000)^2 -> 0.18238355 | U7: =F7*(O7/100*D7/1000)^2 -> 0.20516056 | V7: =SIGN(P7)*F7*(ABS(P7)/100*D7/1000)^2 -> -0.024116833 | W7: =SIGN(Q7)*F7*(ABS(Q7)/100*D7/1000)^2 -> 0.00016747801 | X7: =SIGN(R7)*F7*(ABS(R7)/100*D7/1000)^2 -> -0.0015073021 | Y7: Dumas (2015). Replaces Dumas 2007 combined 'Torso' row. L=313mm (CJC to TJC). Origin=CJC. Cross-check: comY=-52.8%×313=-165.3mm; Table 1 COM Y=-165mm ✓. Mass 26.3%+Abdomen 4.1%=30.4% = 2007 Torso exactly ✓. rxy=12(i)=negative. rxz=3(i)=negative.
A8: Abdomen | B8: 1 | C8: Dumas 2015 ✓ | D8: 121 | E8: 4.1 | F8: =E8/100*$B$1 -> 2.665 | G8: 24.4 | H8: -41.5 | I8: 0.5 | J8: =D8*G8/100 -> 29.524 | K8: =D8*H8/100 -> -50.215 | L8: =D8*I8/100 -> 0.605 | M8: 67 | N8: 77 | O8: 55 | P8: 20 | Q8: -5 | R8: -3 | S8: =F8*(M8/100*D8/1000)^2 -> 0.017515299 | T8: =F8*(N8/100*D8/1000)^2 -> 0.023133929 | U8: =F8*(O8/100*D8/1000)^2 -> 0.011803025 | V8: =SIGN(P8)*F8*(ABS(P8)/100*D8/1000)^2 -> 0.0015607306 | W8: =SIGN(Q8)*F8*(ABS(Q8)/100*D8/1000)^2 -> -9.7545662e-05 | X8: =SIGN(R8)*F8*(ABS(R8)/100*D8/1000)^2 -> -3.5116438e-05 | Y8: Dumas (2015). NEW segment — no 2007 equivalent. L=121mm (TJC to LJC). Origin=TJC. Segment covers trunk below 10th ribs to iliocristales (~L1–L4 level). NOT equivalent to de Leva 'middle trunk'. Cross-check: comY=-41.5%×121=-50.2mm; Table 1 COM Y=-50mm ✓. rxz=3(i)=negative. ryz=5(i)=negative.
A9: Pelvis | B9: 1 | C9: Dumas 2007 ✓ | D9: 107 | E9: 14.6 | F9: =E9/100*$B$1 -> 9.49 | G9: -0.9 | H9: -23.2 | I9: 0.2 | J9: =D9*G9/100 -> -0.963 | K9: =D9*H9/100 -> -24.824 | L9: =D9*I9/100 -> 0.214 | M9: 91 | N9: 100 | O9: 79 | P9: -34 | Q9: -1 | R9: -10 | S9: =F9*(M9/100*D9/1000)^2 -> 0.089973901 | T9: =F9*(N9/100*D9/1000)^2 -> 0.10865101 | U9: =F9*(O9/100*D9/1000)^2 -> 0.067809095 | V9: =SIGN(P9)*F9*(ABS(P9)/100*D9/1000)^2 -> -0.012560057 | W9: =SIGN(Q9)*F9*(ABS(Q9)/100*D9/1000)^2 -> -1.0865101e-05 | X9: =SIGN(R9)*F9*(ABS(R9)/100*D9/1000)^2 -> -0.0010865101 | Y9: ACTIVE WORKSTREAM. L=107 mm (LJC → projection of HJC in sagittal plane). Alternative: L=Pelvis Width (RASIS-LASIS). Origin=LJC. Segment mass covers entire pelvis segment (bone + soft tissue + hardware + battery + flesh + skin) — NOT the ~8 kg structural assembly alone. CoM y=−23.2% of L below LJC (posterior/inferior). CoM x=−0.9% (very small AP offset). rxy=34(i)=negative. rxz=10(i)=negative. ryz=1(i)=negative.
A10: Upper Arm | B10: 2 | C10: Dumas 2007 ✓ | D10: 243 | E10: 2.2 | F10: =E10/100*$B$1 -> 1.43 | G10: -7.3 | H10: -45.4 | I10: -2.8 | J10: =D10*G10/100 -> -17.739 | K10: =D10*H10/100 -> -110.322 | L10: =D10*I10/100 -> -6.804 | M10: 33 | N10: 17 | O10: 33 | P10: 3 | Q10: -4 | R10: -5 | S10: =F10*(M10/100*D10/1000)^2 -> 0.0091955236 | T10: =F10*(N10/100*D10/1000)^2 -> 0.002440318 | U10: =F10*(O10/100*D10/1000)^2 -> 0.0091955236 | V10: =SIGN(P10)*F10*(ABS(P10)/100*D10/1000)^2 -> 7.5996063e-05 | W10: =SIGN(Q10)*F10*(ABS(Q10)/100*D10/1000)^2 -> -0.00013510411 | X10: =SIGN(R10)*F10*(ABS(R10)/100*D10/1000)^2 -> -0.00021110017 | Y10: Dumas 2007, Arm segment. L=243 F. Origin=SJC. rxz=5(i)=negative. ryz=4(i)=negative.
A11: Forearm | B11: 2 | C11: Dumas 2007 ✓ | D11: 271 | E11: 1.3 | F11: =E11/100*$B$1 -> 0.845 | G11: 1.7 | H11: -45.2 | I11: -2.6 | J11: =D11*G11/100 -> 4.607 | K11: =D11*H11/100 -> -122.492 | L11: =D11*I11/100 -> -7.046 | M11: 31 | N11: 14 | O11: 32 | P11: 6 | Q11: 2 | R11: 5 | S11: =F11*(M11/100*D11/1000)^2 -> 0.0059637397 | T11: =F11*(N11/100*D11/1000)^2 -> 0.0012163298 | U11: =F11*(O11/100*D11/1000)^2 -> 0.0063547028 | V11: =SIGN(P11)*F11*(ABS(P11)/100*D11/1000)^2 -> 0.00022340752 | W11: =SIGN(Q11)*F11*(ABS(Q11)/100*D11/1000)^2 -> 2.4823058e-05 | X11: =SIGN(R11)*F11*(ABS(R11)/100*D11/1000)^2 -> 0.00015514411 | Y11: Dumas 2007. L=271 F. Origin=EJC.
A12: Hand | B12: 2 | C12: Dumas 2007 ✓ | D12: 283 | E12: 1.3 | F12: =E12/100*$B$1 -> 0.845 | G12: 1 | H12: -41.7 | I12: 1.4 | J12: =D12*G12/100 -> 2.83 | K12: =D12*H12/100 -> -118.011 | L12: =D12*I12/100 -> 3.962 | M12: 28 | N12: 11 | O12: 27 | P12: 3 | Q12: -1 | R12: 1 | S12: =F12*(M12/100*D12/1000)^2 -> 0.0053057361 | T12: =F12*(N12/100*D12/1000)^2 -> 0.00081886998 | U12: =F12*(O12/100*D12/1000)^2 -> 0.0049335224 | V12: =SIGN(P12)*F12*(ABS(P12)/100*D12/1000)^2 -> 6.0907685e-05 | W12: =SIGN(Q12)*F12*(ABS(Q12)/100*D12/1000)^2 -> -6.7675205e-06 | X12: =SIGN(R12)*F12*(ABS(R12)/100*D12/1000)^2 -> 6.7675205e-06 | Y12: Dumas 2007. L=283 F (WJC to midpoint MH2-MH5). Origin=WJC. ryz=1(i)=negative.
A13: Thigh | B13: 2 | C13: Dumas 2007 ✓ | D13: 432 | E13: 12.3 | F13: =E13/100*$B$1 -> 7.995 | G13: -4.1 | H13: -42.9 | I13: 3.3 | J13: =D13*G13/100 -> -17.712 | K13: =D13*H13/100 -> -185.328 | L13: =D13*I13/100 -> 14.256 | M13: 29 | N13: 15 | O13: 30 | P13: 7 | Q13: -7 | R13: 2 | S13: =F13*(M13/100*D13/1000)^2 -> 0.12548215 | T13: =F13*(N13/100*D13/1000)^2 -> 0.033571325 | U13: =F13*(O13/100*D13/1000)^2 -> 0.1342853 | V13: =SIGN(P13)*F13*(ABS(P13)/100*D13/1000)^2 -> 0.0073110885 | W13: =SIGN(Q13)*F13*(ABS(Q13)/100*D13/1000)^2 -> -0.0073110885 | X13: =SIGN(R13)*F13*(ABS(R13)/100*D13/1000)^2 -> 0.00059682355 | Y13: Dumas 2007. L=432 F. Origin=HJC. ryz=7(i)=negative.
A14: Leg (shank) | B14: 2 | C14: Dumas 2007 ✓ | D14: 388 | E14: 4.5 | F14: =E14/100*$B$1 -> 2.925 | G14: -4.9 | H14: -40.4 | I14: 3.1 | J14: =D14*G14/100 -> -19.012 | K14: =D14*H14/100 -> -156.752 | L14: =D14*I14/100 -> 12.028 | M14: 28 | N14: 10 | O14: 28 | P14: 2 | Q14: -2 | R14: 1 | S14: =F14*(M14/100*D14/1000)^2 -> 0.03452275 | T14: =F14*(N14/100*D14/1000)^2 -> 0.004403412 | U14: =F14*(O14/100*D14/1000)^2 -> 0.03452275 | V14: =SIGN(P14)*F14*(ABS(P14)/100*D14/1000)^2 -> 0.00017613648 | W14: =SIGN(Q14)*F14*(ABS(Q14)/100*D14/1000)^2 -> -0.00017613648 | X14: =SIGN(R14)*F14*(ABS(R14)/100*D14/1000)^2 -> 4.403412e-05 | Y14: Dumas 2007. L=388 F. Origin=KJC. ryz=2(i)=negative.
A15: Foot | B15: 2 | C15: Dumas 2007 ✓ | D15: 165 | E15: 1 | F15: =E15/100*$B$1 -> 0.65 | G15: 27 | H15: -21.8 | I15: 3.9 | J15: =D15*G15/100 -> 44.55 | K15: =D15*H15/100 -> -35.97 | L15: =D15*I15/100 -> 6.435 | M15: 17 | N15: 36 | O15: 35 | P15: -6 | Q15: -4 | R15: 6 | S15: =F15*(M15/100*D15/1000)^2 -> 0.00051142162 | T15: =F15*(N15/100*D15/1000)^2 -> 0.002293434 | U15: =F15*(O15/100*D15/1000)^2 -> 0.0021677906 | V15: =SIGN(P15)*F15*(ABS(P15)/100*D15/1000)^2 -> -6.37065e-05 | W15: =SIGN(Q15)*F15*(ABS(Q15)/100*D15/1000)^2 -> -2.8314e-05 | X15: =SIGN(R15)*F15*(ABS(R15)/100*D15/1000)^2 -> 6.37065e-05 | Y15: Dumas 2007. L=165 F (AJC to midpoint MH1-MHV). Origin=AJC. rxy=6(i)=negative. ryz=4(i)=negative.
F16: =E16/100*$B$1 -> 0
A17: Σ count-weighted mass fraction | E17: =SUMPRODUCT(B6:B15,E6:E15) -> 96.9 | F17: =E17*$B$1 -> 6298.5 | G17: =IF(ABS(E17-1)<=0.02,"OK","CHECK SUM") -> CHECK SUM | Y17: Reconstructed mass (col F) should ≈ total body mass once all fractions are entered. Transcription tripwire.

Sheet Validation
A1: Validation — target (from BSIP Reference) vs achieved (from Fusion mass properties)
A2: Paste Fusion values into yellow 'ach' cells. Deviations compute. Log deliberate departures in the rightmost column.
B4: Mass (kg) | E4: CoM x (mm) | H4: CoM y (mm) | K4: CoM z (mm) | N4: Ixx (kg·m²) | Q4: Iyy (kg·m²) | T4: Izz (kg·m²)
A5: Segment | B5: tgt | C5: ach | D5: Δ | E5: tgt | F5: ach | G5: Δ | H5: tgt | I5: ach | J5: Δ | K5: tgt | L5: ach | M5: Δ | N5: tgt | O5: ach | P5: Δ | Q5: tgt | R5: ach | S5: Δ | T5: tgt | U5: ach | V5: Δ | W5: Deviation log / notes
A6: ='BSIP Reference'!A6 -> Head & Neck | B6: ='BSIP Reference'!F6 -> 4.355 | D6: =C6-B6 -> -4.355 | E6: ='BSIP Reference'!J6 -> 4.048 | G6: =F6-E6 -> -4.048 | H6: ='BSIP Reference'!K6 -> 145.475 | J6: =I6-H6 -> -145.475 | K6: ='BSIP Reference'!L6 -> 0.253 | M6: =L6-K6 -> -0.253 | N6: ='BSIP Reference'!S6 -> 0.023443648 | P6: =O6-N6 -> -0.023443648 | Q6: ='BSIP Reference'!T6 -> 0.014746361 | S6: =R6-Q6 -> -0.014746361 | T6: ='BSIP Reference'!U6 -> 0.025088328 | V6: =U6-T6 -> -0.025088328
A7: ='BSIP Reference'!A7 -> Thorax | B7: ='BSIP Reference'!F7 -> 17.095 | D7: =C7-B7 -> -17.095 | E7: ='BSIP Reference'!J7 -> 6.573 | G7: =F7-E7 -> -6.573 | H7: ='BSIP Reference'!K7 -> -165.264 | J7: =I7-H7 -> 165.264 | K7: ='BSIP Reference'!L7 -> 0.313 | M7: =L7-K7 -> -0.313 | N7: ='BSIP Reference'!S7 -> 0.25473405 | P7: =O7-N7 -> -0.25473405 | Q7: ='BSIP Reference'!T7 -> 0.18238355 | S7: =R7-Q7 -> -0.18238355 | T7: ='BSIP Reference'!U7 -> 0.20516056 | V7: =U7-T7 -> -0.20516056
A8: ='BSIP Reference'!A8 -> Abdomen | B8: ='BSIP Reference'!F8 -> 2.665 | D8: =C8-B8 -> -2.665 | E8: ='BSIP Reference'!J8 -> 29.524 | G8: =F8-E8 -> -29.524 | H8: ='BSIP Reference'!K8 -> -50.215 | J8: =I8-H8 -> 50.215 | K8: ='BSIP Reference'!L8 -> 0.605 | M8: =L8-K8 -> -0.605 | N8: ='BSIP Reference'!S8 -> 0.017515299 | P8: =O8-N8 -> -0.017515299 | Q8: ='BSIP Reference'!T8 -> 0.023133929 | S8: =R8-Q8 -> -0.023133929 | T8: ='BSIP Reference'!U8 -> 0.011803025 | V8: =U8-T8 -> -0.011803025
A9: ='BSIP Reference'!A9 -> Pelvis | B9: ='BSIP Reference'!F9 -> 9.49 | D9: =C9-B9 -> -9.49 | E9: ='BSIP Reference'!J9 -> -0.963 | G9: =F9-E9 -> 0.963 | H9: ='BSIP Reference'!K9 -> -24.824 | J9: =I9-H9 -> 24.824 | K9: ='BSIP Reference'!L9 -> 0.214 | M9: =L9-K9 -> -0.214 | N9: ='BSIP Reference'!S9 -> 0.089973901 | P9: =O9-N9 -> -0.089973901 | Q9: ='BSIP Reference'!T9 -> 0.10865101 | S9: =R9-Q9 -> -0.10865101 | T9: ='BSIP Reference'!U9 -> 0.067809095 | V9: =U9-T9 -> -0.067809095 | W9: Target CoM y/x are the reference for the post-spinal-interface weighted-CoM check. Recall current blue marker ~71 mm posterior of anterior ASIS, ~57% from anterior skin — log AP deviation + control cost here.
A10: ='BSIP Reference'!A10 -> Upper Arm | B10: ='BSIP Reference'!F10 -> 1.43 | D10: =C10-B10 -> -1.43 | E10: ='BSIP Reference'!J10 -> -17.739 | G10: =F10-E10 -> 17.739 | H10: ='BSIP Reference'!K10 -> -110.322 | J10: =I10-H10 -> 110.322 | K10: ='BSIP Reference'!L10 -> -6.804 | M10: =L10-K10 -> 6.804 | N10: ='BSIP Reference'!S10 -> 0.0091955236 | P10: =O10-N10 -> -0.0091955236 | Q10: ='BSIP Reference'!T10 -> 0.002440318 | S10: =R10-Q10 -> -0.002440318 | T10: ='BSIP Reference'!U10 -> 0.0091955236 | V10: =U10-T10 -> -0.0091955236
A11: ='BSIP Reference'!A11 -> Forearm | B11: ='BSIP Reference'!F11 -> 0.845 | D11: =C11-B11 -> -0.845 | E11: ='BSIP Reference'!J11 -> 4.607 | G11: =F11-E11 -> -4.607 | H11: ='BSIP Reference'!K11 -> -122.492 | J11: =I11-H11 -> 122.492 | K11: ='BSIP Reference'!L11 -> -7.046 | M11: =L11-K11 -> 7.046 | N11: ='BSIP Reference'!S11 -> 0.0059637397 | P11: =O11-N11 -> -0.0059637397 | Q11: ='BSIP Reference'!T11 -> 0.0012163298 | S11: =R11-Q11 -> -0.0012163298 | T11: ='BSIP Reference'!U11 -> 0.0063547028 | V11: =U11-T11 -> -0.0063547028
A12: ='BSIP Reference'!A12 -> Hand | B12: ='BSIP Reference'!F12 -> 0.845 | D12: =C12-B12 -> -0.845 | E12: ='BSIP Reference'!J12 -> 2.83 | G12: =F12-E12 -> -2.83 | H12: ='BSIP Reference'!K12 -> -118.011 | J12: =I12-H12 -> 118.011 | K12: ='BSIP Reference'!L12 -> 3.962 | M12: =L12-K12 -> -3.962 | N12: ='BSIP Reference'!S12 -> 0.0053057361 | P12: =O12-N12 -> -0.0053057361 | Q12: ='BSIP Reference'!T12 -> 0.00081886998 | S12: =R12-Q12 -> -0.00081886998 | T12: ='BSIP Reference'!U12 -> 0.0049335224 | V12: =U12-T12 -> -0.0049335224
A13: ='BSIP Reference'!A13 -> Thigh | B13: ='BSIP Reference'!F13 -> 7.995 | D13: =C13-B13 -> -7.995 | E13: ='BSIP Reference'!J13 -> -17.712 | G13: =F13-E13 -> 17.712 | H13: ='BSIP Reference'!K13 -> -185.328 | J13: =I13-H13 -> 185.328 | K13: ='BSIP Reference'!L13 -> 14.256 | M13: =L13-K13 -> -14.256 | N13: ='BSIP Reference'!S13 -> 0.12548215 | P13: =O13-N13 -> -0.12548215 | Q13: ='BSIP Reference'!T13 -> 0.033571325 | S13: =R13-Q13 -> -0.033571325 | T13: ='BSIP Reference'!U13 -> 0.1342853 | V13: =U13-T13 -> -0.1342853
A14: ='BSIP Reference'!A14 -> Leg (shank) | B14: ='BSIP Reference'!F14 -> 2.925 | D14: =C14-B14 -> -2.925 | E14: ='BSIP Reference'!J14 -> -19.012 | G14: =F14-E14 -> 19.012 | H14: ='BSIP Reference'!K14 -> -156.752 | J14: =I14-H14 -> 156.752 | K14: ='BSIP Reference'!L14 -> 12.028 | M14: =L14-K14 -> -12.028 | N14: ='BSIP Reference'!S14 -> 0.03452275 | P14: =O14-N14 -> -0.03452275 | Q14: ='BSIP Reference'!T14 -> 0.004403412 | S14: =R14-Q14 -> -0.004403412 | T14: ='BSIP Reference'!U14 -> 0.03452275 | V14: =U14-T14 -> -0.03452275
A15: ='BSIP Reference'!A15 -> Foot | B15: ='BSIP Reference'!F15 -> 0.65 | D15: =C15-B15 -> -0.65 | E15: ='BSIP Reference'!J15 -> 44.55 | G15: =F15-E15 -> -44.55 | H15: ='BSIP Reference'!K15 -> -35.97 | J15: =I15-H15 -> 35.97 | K15: ='BSIP Reference'!L15 -> 6.435 | M15: =L15-K15 -> -6.435 | N15: ='BSIP Reference'!S15 -> 0.00051142162 | P15: =O15-N15 -> -0.00051142162 | Q15: ='BSIP Reference'!T15 -> 0.002293434 | S15: =R15-Q15 -> -0.002293434 | T15: ='BSIP Reference'!U15 -> 0.0021677906 | V15: =U15-T15 -> -0.0021677906

Sheet Joint Sources & Conventions
A1: Freyja — Joint Definitions: Sources & Conventions
A3: FRAMEWORK COMMITMENT (locked)
A4: JCS framework | B4: ISB Joint Coordinate System. Anchors every joint frame + sign convention. Keeps the joint sheet coherent with the Dumas segment frames the BSIP values already live in.
A5: Joint centres — default | B5: Reed et al. (1999) regressions for trunk centres (CJC, TJC, SJC, LJC). Female coefficients already completed in your Dumas (2007) appendix — pull from there, not Reed directly.
A6: Joint centres — override | B6: Harrington et al. (2007) for the HJC. Better-validated, pelvic-geometry driven. Reed↔Harrington HJC offset (few mm) logged as a deviation, not silently absorbed.
A7: Other JCs | B7: Knee/ankle/elbow/wrist = landmark midpoints (epicondyles, malleoli, styloids), per ISB SCS definitions — not regressions.
A8: ROM — anatomical ceiling | B8: Soucie et al. (2011), female-inclusive. Boone & Azen (1979) secondary/historical (male-only — population mismatch).
A9: ROM — functional target | B9: Winter (level gait, you have it); Riener et al. (2002) for stair descent/ascent; task kinematics per movement.
A10: FRAME COHERENCE RULE | B10: Joint frames MUST match the Dumas SCS the BSIP tensors are expressed in. A joint frame defined differently than its segment frame = every inertia number off by a transform. This is the whole reason ISB was chosen.
A12: VERIFIED CITATIONS (DOIs confirmed from primary sources)
A13: Source | B13: Title (abbrev.) | C13: Year / venue | D13: DOI / PMID | E13: Used for
A14: Wu et al. 2002 | B14: ISB JCS part I: ankle, hip, spine | C14: J Biomech 35(4):543–548 | D14: 10.1016/s0021-9290(01)00222-6 | E14: Frames: hip, ankle, lumbosacral, spine
A15: Wu et al. 2005 | B15: ISB JCS part II: shoulder, elbow, wrist, hand | C15: J Biomech 38(5):981–992 | D15: 10.1016/j.jbiomech.2004.05.042 | E15: Frames: upper limb (later)
A16: Grood & Suntay 1983 | B16: JCS for 3D motion: knee | C16: J Biomech Eng 105(2):136–144 | D16: 10.1115/1.3138397 | E16: Frame + rotation sequence: knee
A17: Reed et al. 1999 | B17: Measuring/representing occupant posture | C17: SAE 1999-01-0959 | D17: 10.4271/1999-01-0959 | E17: Trunk JC method (female coeffs in Dumas appx)
A18: Harrington et al. 2007 | B18: Prediction of the hip joint centre (MRI) | C18: J Biomech 40(3):595–602 | D18: 10.1016/j.jbiomech.2006.02.003 | E18: HJC override (primary)
A19: Soucie et al. 2011 | B19: ROM reference values & database | C19: Haemophilia 17(3):500–507 | D19: 10.1111/j.1365-2516.2010.02399.x | E19: ROM anatomical ceiling (primary)
A20: Boone & Azen 1979 | B20: Normal ROM of joints in male subjects | C20: JBJS Am 61(5):756–759 | D20: PMID 457719 | E20: ROM ceiling (secondary; male-only)
A21: Riener et al. 2002 | B21: Stair ascent/descent at different inclinations | C21: Gait Posture 15(1):32–44 | D21: 10.1016/s0966-6362(01)00162-x | E21: ROM functional (stairs)
A23: CONVENTIONS
A24: Rotation sequence | B24: ISB Cardan/Euler per joint. Grood–Suntay floating-axis convention: e1 = flexion axis fixed in proximal segment; e3 = long axis fixed in distal segment; e2 = floating axis (e3 × e1), carries ab/adduction.
A25: Sign conventions | B25: + flexion, + adduction, + internal rotation (right side); mirror for left. State explicit per joint in the Definitions sheet — do not assume.
A26: Reference pose | B26: Anatomical neutral standing = all joint angles zero.
A27: Units | B27: Angles in degrees. JC coordinates in mm, expressed in the PROXIMAL segment frame. ROM in degrees.
A28: Population provenance | B28: Soucie = mixed-sex, ages 2–69. Boone & Azen = male only. Reed/Dumas = young adult. Harrington = mixed adults+children, MRI. Document, don't assume median.

Sheet Joint Definitions
A1: Joint | B1: Proximal segment | C1: Distal segment | D1: JC source (policy) | E1: JC placement / regression | F1: SCS origin | G1: e1 axis (proximal) + motion | H1: e2 axis (floating) + motion | I1: e3 axis (distal) + motion | J1: Rotation sequence | K1: Sign conventions | L1: Axis obliquity / non-orthogonality | M1: Freyja status / deviation log | N1: Source
A2: Hip | B2: Pelvis | C2: Thigh | D2: Harrington 2007 (override) | E2: HJC via Harrington (2007) single-variable regression (eq 5–7), RIGHT hip, mm, in the ASIS-midpoint pelvic frame (x ant, y sup, z right): x̂ = −0.24·PD − 9.9 (antero-posterior) ŷ = −0.30·PW − 10.9 (supero-inferior) ẑ = +0.33·PW + 7.3 (medio-lateral) LEFT hip: negate ẑ. PW = inter-ASIS width; PD = ASIS-midpoint→PSIS-midpoint distance. ORIGIN = midpoint of the two ASIS (NOT the HJC). The located HJC then becomes the origin of the Wu/Dumas pelvic JCS frame. LOOCV error ≈5 mm (AP), ≈4 mm (SI, ML). Multi-var alt for y: ŷ=−0.16·PW−0.04·LL−7.1. | F2: Right (or left) hip joint centre (HJC) | G2: Z (pelvic CS): ∥ line joining R & L ASIS, points right. Rotation α = flexion / extension | H2: Floating axis ⊥ e1 & e3. Rotation β = adduction / abduction | I2: y (femoral CS): FE-midpoint → HJC, points cranial. Rotation γ = internal / external rotation | J2: e1→e2→e3: Z (flex/ext) → floating (add/abd) → y (int/ext rot) | K2: Right-handed frames as defined. Wu 2002 gives no explicit polarity for hip; adopt JCS standard: +flexion about +Z, +adduction, +internal rotation (right); mirror left. | L2: Ball-and-socket; 3 rotational DOF treated as orthogonal in the JCS. No obliquity correction. | M2: Pelvic CS = Dumas pelvis SCS exactly → coherent with BSIP, no transform. HJC LOCATED via Harrington 2007 (eq 5–7); output is relative to the ASIS-midpoint, and that located point becomes the JCS/BSIP frame origin. CROSS-CHECK vs locked inter-HJC 173.2 mm: inter-HJC = 0.66·PW + 14.6 ⇒ implies inter-ASIS PW ≈ 240 mm (each HJC 86.6 mm lateral of ASIS midpoint). Verify against CAD/MakeHuman pelvic width before joint freeze. Note: Harrington needs PD & PW — soft-tissue-biased in gait labs, but you have TRUE bony values from CAD, so it is cleaner for Freyja than for its validation population. | N2: Wu 2002 + Harrington
A3: Knee | B3: Thigh | C3: Leg (shank) | D3: Landmark midpoint (epicondyles) | E3: KJC = femoral epicondyle midpoint (motion-analysis convention, matches policy). G&S original locates origins on the mechanical axes through the intercondylar points (from biplanar X-ray); for Freyja use the epicondyle-midpoint KJC to stay coherent with the Dumas thigh/shank frames. | F3: KJC = femoral epicondyle midpoint. [G&S original: tibial mechanical axis where it crosses subchondral bone between the intercondylar eminences.] | G3: e1 = femoral mediolateral axis (through condyles/epicondyles), fixed in femur, points right. Rotation α = flexion (+) / extension (−). [G&S label: e1 = I; reference e1ʳ = J anterior] | H3: e2 = floating axis = (e3 × e1)/|e3 × e1|, common perpendicular. Rotation β = abduction (+) / adduction (−). Magnitude via cos β = I·k; sign is side-dependent (R: adduction = β − π/2; L: π/2 − β). | I3: e3 = tibial long (mechanical) axis, fixed in tibia, points proximal. Rotation γ = external rotation (+) / internal rotation (−). [G&S label: e3 = k; reference e3ʳ = j anterior] | J3: e1→e2→e3: flexion (femoral ML) → ab/adduction (floating) → int/ext rotation (tibial long axis). SEQUENCE-INDEPENDENT — the central G&S result: JCS angles do not depend on decomposition order (unlike Euler angles). | K3: Per G&S Fig 3 (right knee): flexion +, abduction +, external rotation +. Side-dependent flips for ab/adduction and tibial rotation (L vs R). Translations: lateral tibial shift q1 +, anterior drawer q2 +, joint distraction q3 +. | L3: Flexion axis e1 is NOT the screw axis — the screw/helical axis is skewed (it combines tibial rotation + adduction with flexion). G&S deliberately separate the clinical flexion axis from the screw axis. e1 ⊥ e3 only at neutral; off-neutral the system is non-orthogonal, coupling translations (e.g. distraction along e3 also shifts ML). Singularity at β=0 (90° abduction) / gimbal lock — non-issue for the knee, but watch it at the shoulder. | M3: FRAMEWORK SOURCE for the whole sheet — every other joint inherits this e1/e2/e3 floating-axis JCS. Build the femoral & tibial Cartesian frames as the Dumas thigh/shank segment frames for BSIP coherence (e1 = ML/right axis, e3 = long/proximal axis). NB: G&S's 'four-link cylindrical chain' (Fig 6) is the JCS's kinematic abstraction — distinct from your anatomical crossed-four-bar ACL/PCL knee linkage; don't conflate. | N3: Grood & Suntay 1983
A4: Ankle (talocrural) | B4: Leg (shank) | C4: Foot | D4: Landmark midpoint (malleoli) | E4: Origin = IM (inter-malleolar point, midway MM–LM tips). Landmark midpoint, per ISB. | F4: IM — inter-malleolar point (midway MM–LM) | G4: Z (tibia/fibula CS): line MM→LM, points right. Rotation α = dorsiflexion (+) / plantarflexion (−) | H4: Floating axis ⊥ e1 & e3. Rotation β = inversion (+) / eversion (−) | I4: y (calcaneus CS): long axis of tibia/fibula in neutral, points cranial. Rotation γ = internal (+) / external (−) rotation | J4: e1→e2→e3: Z (dorsi/plantar) → floating (inv/ev) → y (int/ext rot) | K4: Dorsiflexion +, inversion +, internal rotation + (right). Translations: lateral shift +, anterior drawer +, compression +. | L4: This is the ANKLE COMPLEX (talocrural + subtalar LUMPED) — ISB deferred separate talocrural/subtalar standards. Real talocrural & subtalar axes are oblique; matters when the ankle is split for actuation. | M4: Foot-to-shank lumped complex. For Freyja's actuated ankle, decide: model talocrural + subtalar separately (oblique axes) vs lumped single axis. | N4: Wu 2002
A5: Lumbosacral (L5/S1) | B5: Pelvis | C5: Abdomen | D5: Reed 1999 / Dumas appx (LJC) | E5: Origin = LJC (lumbar joint centre). From Reed 1999 / Dumas female appendix. | F5: LJC (proximal joint centre); regional application of intervertebral JCS | G5: Z (proximal segment CS): ∥ pedicle-base line, points right. Rotation α = flexion / extension | H5: Floating axis ⊥ e1 & e3. Rotation β = lateral bending | I5: y (distal segment CS): through vertebral endplate centres, points cephalad. Rotation γ = axial rotation | J5: e1→e2→e3: Z (flex/ext) → floating (lateral bend) → y (axial rot) | K5: Right-handed as defined. Wu 2002 spine assigns no explicit polarity; adopt +flexion, +right lateral bending, +rightward axial rotation. | L5: CRITICAL: intervertebral joints have NO fixed axis — only an instantaneous axis of rotation. 6-DOF with coupling (off-diagonal stiffness; Panjabi 1976). Helical axis is the alternative. Regional value = summation over levels. | M5: Directly relevant to continuum-spine work: ISB itself treats spine motion as no-fixed-axis + coupled DOF. If the spine participates in balance, this coupling must be present in the MuJoCo model. | N5: Wu 2002 + Dumas
A6: Thoracolumbar (TJC) | B6: Abdomen | C6: Thorax | D6: Dumas 2015 (TJC) | E6: Origin = TJC (thoracic joint centre). From Dumas 2015. | F6: TJC (proximal joint centre); regional intervertebral JCS | G6: Z (proximal segment CS): ∥ pedicle-base line, points right. Rotation α = flexion / extension | H6: Floating axis ⊥ e1 & e3. Rotation β = lateral bending | I6: y (distal segment CS): through vertebral endplate centres, points cephalad. Rotation γ = axial rotation | J6: e1→e2→e3: Z (flex/ext) → floating (lateral bend) → y (axial rot) | K6: Right-handed as defined. Wu 2002 spine assigns no explicit polarity; adopt +flexion, +right lateral bending, +rightward axial rotation. | L6: CRITICAL: intervertebral joints have NO fixed axis — only an instantaneous axis of rotation. 6-DOF with coupling (off-diagonal stiffness; Panjabi 1976). Helical axis is the alternative. Regional value = summation over levels. | M6: Spine JCS (regional). TJC from Dumas 2015 — coherent with BSIP thorax/abdomen frames. | N6: Wu 2002 + Dumas 2015
A7: Cervical (CJC) | B7: Thorax | C7: Head & Neck | D7: Reed 1999 / Dumas appx (CJC) | E7: Origin = CJC (cervical joint centre). From Reed 1999 / Dumas female appendix. | F7: CJC (proximal joint centre); regional intervertebral JCS | G7: Z (proximal segment CS): ∥ pedicle-base line, points right. Rotation α = flexion / extension | H7: Floating axis ⊥ e1 & e3. Rotation β = lateral bending | I7: y (distal segment CS): through vertebral endplate centres, points cephalad. Rotation γ = axial rotation | J7: e1→e2→e3: Z (flex/ext) → floating (lateral bend) → y (axial rot) | K7: Right-handed as defined. Wu 2002 spine assigns no explicit polarity; adopt +flexion, +right lateral bending, +rightward axial rotation. | L7: CRITICAL: intervertebral joints have NO fixed axis — only an instantaneous axis of rotation. 6-DOF with coupling (off-diagonal stiffness; Panjabi 1976). Helical axis is the alternative. Regional value = summation over levels. | M7: Spine JCS (regional). CJC from Reed/Dumas. | N7: Wu 2002 + Dumas
A8: Shoulder (GH) | B8: Thorax | C8: Upper Arm | D8: Reed 1999 / Dumas appx (SJC) | N8: Wu 2005 + Dumas
A9: Elbow | B9: Upper Arm | C9: Forearm | D9: Landmark midpoint (epicondyles) | N9: Wu 2005
A10: Wrist | B10: Forearm | C10: Hand | D10: Landmark midpoint (styloids) | N10: Wu 2005
A12: Pre-filled (blue-grey) = locked decisions. Yellow = populate from the paper named in the Source column.

Sheet Joint ROM
A1: Joint | B1: Movement | C1: Plane / axis | D1: Anatomical ceiling (°) | E1: Ceiling source | F1: Functional demand (°) | G1: Functional source / task | H1: Freyja target (°) | I1: Hard constraint? | J1: Headroom (°) (ceil − func) | K1: Notes
A2: Hip | B2: Flexion | C2: Sagittal | D2: 133.8 | E2: Soucie 2011 (F, 20–44) | F2: 67 | G2: Riener 2002 — stair ascent | J2: =IF(AND(ISNUMBER(D2),ISNUMBER(F2)),D2-F2,"") -> 66.8 | K2: Soucie ceiling 133.8°. Riener ascent peak ≈67° (30° stairs) up to ~73° (42°). Read off Fig 2 ±~3°. Large positive headroom — anatomy not the limiter.
A3: Hip | B3: Extension | C3: Sagittal | D3: 18.1 | E3: Soucie 2011 (F, 20–44) | F3: low | G3: Riener 2002 — stair descent | J3: =IF(AND(ISNUMBER(D3),ISNUMBER(F3)),D3-F3,"") | K3: Soucie ceiling 18.1°. On stairs the hip stays flexed — extension demand is small (≈0–10°), not governing. No headroom number entered (qualitative).
A4: Hip | B4: Abduction | C4: Frontal | J4: =IF(AND(ISNUMBER(D4),ISNUMBER(F4)),D4-F4,"") | K4: Soucie n/a (no frontal hip). Source needed: Boone&Azen (M) / AAOS.
A5: Hip | B5: Adduction | C5: Frontal | J5: =IF(AND(ISNUMBER(D5),ISNUMBER(F5)),D5-F5,"") | K5: Soucie n/a. Source: Boone&Azen (M) / AAOS.
A6: Hip | B6: Internal rotation | C6: Transverse | J6: =IF(AND(ISNUMBER(D6),ISNUMBER(F6)),D6-F6,"") | K6: Soucie n/a (no hip rotation). Source: Boone&Azen (M) / AAOS.
A7: Hip | B7: External rotation | C7: Transverse | J7: =IF(AND(ISNUMBER(D7),ISNUMBER(F7)),D7-F7,"") | K7: Soucie n/a. Source: Boone&Azen (M) / AAOS.
A8: Knee | B8: Flexion | C8: Sagittal | D8: 141.9 | E8: Soucie 2011 (F, 20–44) | F8: 95 | G8: Riener 2002 — stair descent | J8: =IF(AND(ISNUMBER(D8),ISNUMBER(F8)),D8-F8,"") -> 46.9 | K8: Soucie ceiling 141.9°. Riener descent peak ≈95° (30°) up to ~100° (42°); ascent similar. Large positive headroom anatomically — your four-bar divergence at 120°+ is the real limiter, not human ROM.
A9: Knee | B9: Extension | C9: Sagittal | D9: 1.6 | E9: Soucie 2011 (F, 20–44) | F9: ~0 | G9: Riener 2002 — stair descent | J9: =IF(AND(ISNUMBER(D9),ISNUMBER(F9)),D9-F9,"") | K9: Soucie ceiling 1.6° hyperext. Knee reaches near-full extension in stance but no hyperextension demand on stairs. Keep the 0° hard-stop. No headroom number (qualitative).
A10: Ankle | B10: Dorsiflexion | C10: Sagittal | D10: 13.8 | E10: Soucie 2011 (F, 20–44) | F10: 18 | G10: Riener 2002 — stair descent | H10: 25 | I10: YES | J10: =IF(AND(ISNUMBER(D10),ISNUMBER(F10)),D10-F10,"") -> -4.2 | K10: GOVERNING. Three-way: Soucie ceiling 13.8° (F mean) < Riener descent demand ≈15° (30° stairs) to ~18–20° (42°) < your design target 25°. So stair-descent dorsiflexion ALREADY exceeds the population-MEAN ankle ceiling (headroom negative), which is why stairs need above-average ankle flexibility. Your 25° gives margin above the steepest measured stair demand and sits at ~+2 SD of the female distribution (within the human max of 36°). Design the ankle for the flexible tail, log it as a deliberate above-median departure. Plot reads ±~3°.
A11: Ankle | B11: Plantarflexion | C11: Sagittal | D11: 62.1 | E11: Soucie 2011 (F, 20–44) | F11: 28 | G11: Riener 2002 — stair descent | J11: =IF(AND(ISNUMBER(D11),ISNUMBER(F11)),D11-F11,"") -> 34.1 | K11: Soucie ceiling 62.1°. Riener descent peak plantarflexion ≈25–30° (late stance/push-off). Large positive headroom.
A12: Ankle | B12: Inversion | C12: Frontal | J12: =IF(AND(ISNUMBER(D12),ISNUMBER(F12)),D12-F12,"") | K12: Soucie n/a (no ankle inv/ev). Source: Boone&Azen (M) / AAOS.
A13: Ankle | B13: Eversion | C13: Frontal | J13: =IF(AND(ISNUMBER(D13),ISNUMBER(F13)),D13-F13,"") | K13: Soucie n/a. Source: Boone&Azen (M) / AAOS.
A14: Lumbosacral | B14: Flexion | C14: Sagittal | J14: =IF(AND(ISNUMBER(D14),ISNUMBER(F14)),D14-F14,"") | K14: Soucie n/a (no spine). Source: spine ROM literature / AAOS.
A15: Lumbosacral | B15: Extension | C15: Sagittal | J15: =IF(AND(ISNUMBER(D15),ISNUMBER(F15)),D15-F15,"") | K15: Soucie n/a. Source: spine ROM literature / AAOS.
A16: Lumbosacral | B16: Lateral bending | C16: Frontal | J16: =IF(AND(ISNUMBER(D16),ISNUMBER(F16)),D16-F16,"") | K16: Soucie n/a. Source: spine ROM literature / AAOS.
A17: Lumbosacral | B17: Axial rotation | C17: Transverse | J17: =IF(AND(ISNUMBER(D17),ISNUMBER(F17)),D17-F17,"") | K17: Soucie n/a. Source: spine ROM literature / AAOS.
A18: Shoulder | B18: Flexion | C18: Sagittal | D18: 172 | E18: Soucie 2011 (F, 20–44) | J18: =IF(AND(ISNUMBER(D18),ISNUMBER(F18)),D18-F18,"") | K18: 95% CI 170.9–173.1; SD 6.8; max 183°.
A19: Shoulder | B19: Extension | C19: Sagittal | J19: =IF(AND(ISNUMBER(D19),ISNUMBER(F19)),D19-F19,"") | K19: Soucie n/a (only shoulder flexion). Source: AAOS / Boone&Azen (M).
A20: Shoulder | B20: Abduction | C20: Frontal | J20: =IF(AND(ISNUMBER(D20),ISNUMBER(F20)),D20-F20,"") | K20: Soucie n/a. Source: AAOS / Boone&Azen (M).
A21: Elbow | B21: Flexion | C21: Sagittal | D21: 150 | E21: Soucie 2011 (F, 20–44) | J21: =IF(AND(ISNUMBER(D21),ISNUMBER(F21)),D21-F21,"") | K21: 95% CI 149.1–150.9; SD 5.5; max 165.5°.
A22: Elbow | B22: Extension | C22: Sagittal | D22: 4.7 | E22: Soucie 2011 (F, 20–44) | J22: =IF(AND(ISNUMBER(D22),ISNUMBER(F22)),D22-F22,"") | K22: Hyperextension beyond neutral; SD 4.8; max 18°.
A23: Wrist | B23: Flexion | C23: Sagittal | J23: =IF(AND(ISNUMBER(D23),ISNUMBER(F23)),D23-F23,"") | K23: Soucie n/a (no wrist). Source: Boone&Azen (M) / AAOS.
A24: Wrist | B24: Extension | C24: Sagittal | J24: =IF(AND(ISNUMBER(D24),ISNUMBER(F24)),D24-F24,"") | K24: Soucie n/a. Source: Boone&Azen (M) / AAOS.
A26: Headroom = ceiling − functional. Negative ⇒ task demands more than population-mean anatomy ⇒ Freyja must exceed human-typical ROM there.
